<?xml version="1.0" encoding="UTF-8"?>
<ScriptingToolPreferences doc_version="0">
  <button_hold_time>0.5</button_hold_time>
  <dump_midi>false</dump_midi>
  <configurations>
    <launchpad_recorder_transport>
      <autostart>false</autostart>
      <device_port_in/>
      <device_port_out/>
      <applications>
        <Navigator>
          <options/>
        </Navigator>
        <Transport>
          <options>
            <pattern_play>3</pattern_play>
            <pattern_stop>1.0</pattern_stop>
            <pattern_switch>1.0</pattern_switch>
            <jump_mode>1.0</jump_mode>
          </options>
        </Transport>
        <Mixer_Track>
          <options>
            <track_offset>1.0</track_offset>
            <page_size>1.0</page_size>
            <sync_pre_post>1.0</sync_pre_post>
            <pre_post>1.0</pre_post>
            <follow_track>1.0</follow_track>
            <invert_mute>2</invert_mute>
            <mute_mode>1.0</mute_mode>
          </options>
        </Mixer_Track>
        <Recorder>
          <options>
            <trigger_mode>1.0</trigger_mode>
            <auto_seek>2</auto_seek>
            <beat_sync>1.0</beat_sync>
            <loop_mode>2</loop_mode>
            <autostart>4</autostart>
            <follow_track>2</follow_track>
            <page_size>1.0</page_size>
          </options>
        </Recorder>
        <TrackSelector>
          <options>
            <page_size>1.0</page_size>
          </options>
        </TrackSelector>
        <Mixer>
          <options>
            <track_offset>1.0</track_offset>
            <page_size>1.0</page_size>
            <sync_pre_post>1.0</sync_pre_post>
            <pre_post>1.0</pre_post>
            <follow_track>2</follow_track>
            <invert_mute>2</invert_mute>
            <mute_mode>1.0</mute_mode>
          </options>
        </Mixer>
      </applications>
    </launchpad_recorder_transport>
    <launchpad_mixer_navigator_transport>
      <autostart>false</autostart>
      <device_port_in/>
      <device_port_out/>
      <applications>
        <Navigator>
          <options/>
        </Navigator>
        <Transport>
          <options>
            <pattern_play>3</pattern_play>
            <pattern_stop>1.0</pattern_stop>
            <pattern_switch>1.0</pattern_switch>
            <jump_mode>1.0</jump_mode>
          </options>
        </Transport>
        <Mixer>
          <options>
            <track_offset>1.0</track_offset>
            <page_size>2</page_size>
            <sync_pre_post>1.0</sync_pre_post>
            <pre_post>1.0</pre_post>
            <follow_track>1.0</follow_track>
            <invert_mute>1.0</invert_mute>
            <mute_mode>1.0</mute_mode>
          </options>
        </Mixer>
      </applications>
    </launchpad_mixer_navigator_transport>
    <launchpad_matrix_transport>
      <autostart>false</autostart>
      <device_port_in/>
      <device_port_out/>
      <applications>
        <Transport>
          <options>
            <pattern_play>3</pattern_play>
            <pattern_stop>1.0</pattern_stop>
            <pattern_switch>1.0</pattern_switch>
            <jump_mode>1.0</jump_mode>
          </options>
        </Transport>
        <Matrix>
          <options>
            <switch_mode>2</switch_mode>
            <page_size>1.0</page_size>
            <sequence_mode>2</sequence_mode>
            <follow_track>2</follow_track>
            <bounds_mode>2</bounds_mode>
            <play_mode>3</play_mode>
          </options>
        </Matrix>
      </applications>
    </launchpad_matrix_transport>
    <launchpad_effect_transport>
      <autostart>false</autostart>
      <device_port_in/>
      <device_port_out/>
      <applications>
        <Effect>
          <options>
            <include_parameters>1.0</include_parameters>
          </options>
        </Effect>
        <TrackSelector>
          <options>
            <page_size>3</page_size>
          </options>
        </TrackSelector>
        <Transport>
          <options>
            <pattern_play>3</pattern_play>
            <pattern_stop>1.0</pattern_stop>
            <pattern_switch>1.0</pattern_switch>
            <jump_mode>1.0</jump_mode>
          </options>
        </Transport>
      </applications>
    </launchpad_effect_transport>
    <launchpad_matrix_mixer_transport>
      <autostart>false</autostart>
      <device_port_in/>
      <device_port_out/>
      <applications>
        <Matrix>
          <options>
            <switch_mode>2</switch_mode>
            <page_size>1.0</page_size>
            <sequence_mode>1.0</sequence_mode>
            <follow_track>2</follow_track>
            <bounds_mode>2</bounds_mode>
            <play_mode>3</play_mode>
          </options>
        </Matrix>
        <Transport>
          <options>
            <pattern_play>1.0</pattern_play>
            <pattern_stop>1.0</pattern_stop>
            <pattern_switch>1.0</pattern_switch>
            <jump_mode>1.0</jump_mode>
          </options>
        </Transport>
        <Mixer>
          <options>
            <track_offset>1.0</track_offset>
            <page_size>1.0</page_size>
            <sync_pre_post>1.0</sync_pre_post>
            <pre_post>1.0</pre_post>
            <follow_track>2</follow_track>
            <invert_mute>1.0</invert_mute>
            <mute_mode>1.0</mute_mode>
          </options>
        </Mixer>
      </applications>
    </launchpad_matrix_mixer_transport>
    <launchpad_step_sequencer>
      <autostart>true</autostart>
      <device_port_in/>
      <device_port_out/>
      <applications>
        <StepSequencer>
          <options>
            <page_size>1.0</page_size>
            <vol_dev>1.0</vol_dev>
            <line_increment>8</line_increment>
            <instrument_scheme>1.0</instrument_scheme>
            <follow_track>2</follow_track>
            <humanize>2</humanize>
          </options>
        </StepSequencer>
      </applications>
    </launchpad_step_sequencer>
    <monome_128_mixer_transport>
      <device_port_in/>
      <autostart>false</autostart>
      <device_address/>
      <device_prefix/>
      <device_port_out/>
      <applications>
        <Navigator>
          <options/>
        </Navigator>
        <Transport>
          <options>
            <pattern_play>3</pattern_play>
            <pattern_stop>1.0</pattern_stop>
            <pattern_switch>1.0</pattern_switch>
            <jump_mode>1.0</jump_mode>
          </options>
        </Transport>
        <Mixer>
          <options>
            <track_offset>1.0</track_offset>
            <page_size>1.0</page_size>
            <sync_pre_post>1.0</sync_pre_post>
            <pre_post>1.0</pre_post>
            <follow_track>2</follow_track>
            <invert_mute>2</invert_mute>
            <mute_mode>1.0</mute_mode>
          </options>
        </Mixer>
      </applications>
    </monome_128_mixer_transport>
    <monome_128_matrix_effect>
      <device_port_in/>
      <autostart>false</autostart>
      <device_address/>
      <device_prefix/>
      <device_port_out/>
      <applications>
        <Effect>
          <options>
            <include_parameters>1.0</include_parameters>
          </options>
        </Effect>
        <Matrix>
          <options>
            <switch_mode>2</switch_mode>
            <page_size>1.0</page_size>
            <sequence_mode>1.0</sequence_mode>
            <follow_track>2</follow_track>
            <bounds_mode>2</bounds_mode>
            <play_mode>3</play_mode>
          </options>
        </Matrix>
        <Navigator>
          <options/>
        </Navigator>
        <Transport>
          <options>
            <pattern_play>3</pattern_play>
            <pattern_stop>1.0</pattern_stop>
            <pattern_switch>1.0</pattern_switch>
            <jump_mode>1.0</jump_mode>
          </options>
        </Transport>
      </applications>
    </monome_128_matrix_effect>
    <monome_128_recorder_mixer>
      <device_port_in/>
      <autostart>false</autostart>
      <device_address/>
      <device_prefix/>
      <device_port_out/>
      <applications>
        <Navigator>
          <options/>
        </Navigator>
        <Mixer>
          <options>
            <track_offset>1.0</track_offset>
            <page_size>3</page_size>
            <sync_pre_post>1.0</sync_pre_post>
            <pre_post>1.0</pre_post>
            <follow_track>1.0</follow_track>
            <invert_mute>2</invert_mute>
            <mute_mode>1.0</mute_mode>
          </options>
        </Mixer>
        <Recorder>
          <options>
            <trigger_mode>1.0</trigger_mode>
            <auto_seek>2</auto_seek>
            <beat_sync>1.0</beat_sync>
            <loop_mode>2</loop_mode>
            <autostart>4</autostart>
            <follow_track>1.0</follow_track>
            <page_size>3</page_size>
          </options>
        </Recorder>
        <TrackSelector>
          <options>
            <page_size>1.0</page_size>
          </options>
        </TrackSelector>
        <Transport>
          <options>
            <pattern_play>3</pattern_play>
            <pattern_stop>1.0</pattern_stop>
            <pattern_switch>1.0</pattern_switch>
            <jump_mode>1.0</jump_mode>
          </options>
        </Transport>
      </applications>
    </monome_128_recorder_mixer>
    <monome_128_stepsequencer>
      <device_port_in/>
      <autostart>false</autostart>
      <device_address/>
      <device_prefix/>
      <device_port_out/>
      <applications>
        <Navigator>
          <options/>
        </Navigator>
        <StepSequencer>
          <options>
            <page_size>1.0</page_size>
            <vol_dev>1.0</vol_dev>
            <line_increment>8</line_increment>
            <instrument_scheme>2</instrument_scheme>
            <follow_track>2</follow_track>
            <humanize>1.0</humanize>
          </options>
        </StepSequencer>
        <Transport>
          <options>
            <pattern_play>3</pattern_play>
            <pattern_stop>1.0</pattern_stop>
            <pattern_switch>1.0</pattern_switch>
            <jump_mode>1.0</jump_mode>
          </options>
        </Transport>
      </applications>
    </monome_128_stepsequencer>
    <monome_64_mixer>
      <device_port_in/>
      <autostart>false</autostart>
      <device_address/>
      <device_prefix/>
      <device_port_out/>
      <applications>
        <Mixer>
          <options>
            <track_offset>1.0</track_offset>
            <page_size>1.0</page_size>
            <sync_pre_post>1.0</sync_pre_post>
            <pre_post>1.0</pre_post>
            <follow_track>1.0</follow_track>
            <invert_mute>2</invert_mute>
            <mute_mode>1.0</mute_mode>
          </options>
        </Mixer>
        <Transport>
          <options>
            <pattern_play>3</pattern_play>
            <pattern_stop>1.0</pattern_stop>
            <pattern_switch>1.0</pattern_switch>
            <jump_mode>1.0</jump_mode>
          </options>
        </Transport>
      </applications>
    </monome_64_mixer>
    <monome_64_matrix>
      <device_port_in/>
      <autostart>false</autostart>
      <device_address/>
      <device_prefix/>
      <device_port_out/>
      <applications>
        <Matrix>
          <options>
            <switch_mode>2</switch_mode>
            <page_size>1.0</page_size>
            <sequence_mode>1.0</sequence_mode>
            <follow_track>2</follow_track>
            <bounds_mode>2</bounds_mode>
            <play_mode>3</play_mode>
          </options>
        </Matrix>
      </applications>
    </monome_64_matrix>
    <monome_64_stepsequencer>
      <device_port_in/>
      <autostart>false</autostart>
      <device_address/>
      <device_prefix/>
      <device_port_out/>
      <applications>
        <StepSequencer>
          <options>
            <page_size>1.0</page_size>
            <vol_dev>1.0</vol_dev>
            <line_increment>8</line_increment>
            <instrument_scheme>2</instrument_scheme>
            <follow_track>2</follow_track>
            <humanize>1.0</humanize>
          </options>
        </StepSequencer>
        <Navigator>
          <options/>
        </Navigator>
      </applications>
    </monome_64_stepsequencer>
    <monome_64_recorder>
      <device_port_in/>
      <autostart>false</autostart>
      <device_address/>
      <device_prefix/>
      <device_port_out/>
      <applications>
        <Navigator>
          <options/>
        </Navigator>
        <Recorder>
          <options>
            <trigger_mode>1.0</trigger_mode>
            <auto_seek>2</auto_seek>
            <beat_sync>1.0</beat_sync>
            <loop_mode>2</loop_mode>
            <autostart>4</autostart>
            <follow_track>1.0</follow_track>
            <page_size>1.0</page_size>
          </options>
        </Recorder>
        <TrackSelector>
          <options>
            <page_size>8</page_size>
          </options>
        </TrackSelector>
        <Transport>
          <options>
            <pattern_play>3</pattern_play>
            <pattern_stop>1.0</pattern_stop>
            <pattern_switch>1.0</pattern_switch>
            <jump_mode>1.0</jump_mode>
          </options>
        </Transport>
      </applications>
    </monome_64_recorder>
    <touchosc_mixer_recorder_matrix>
      <device_port_in/>
      <autostart>false</autostart>
      <device_address/>
      <device_prefix/>
      <device_port_out/>
      <applications>
        <Recorder>
          <options>
            <trigger_mode>1.0</trigger_mode>
            <auto_seek>2</auto_seek>
            <beat_sync>1.0</beat_sync>
            <loop_mode>2</loop_mode>
            <autostart>4</autostart>
            <follow_track>2</follow_track>
            <page_size>1.0</page_size>
          </options>
        </Recorder>
        <Matrix>
          <options>
            <switch_mode>2</switch_mode>
            <page_size>1.0</page_size>
            <sequence_mode>2</sequence_mode>
            <follow_track>2</follow_track>
            <bounds_mode>2</bounds_mode>
            <play_mode>3</play_mode>
          </options>
        </Matrix>
        <Mixer>
          <options>
            <track_offset>1.0</track_offset>
            <page_size>1.0</page_size>
            <sync_pre_post>1.0</sync_pre_post>
            <pre_post>1.0</pre_post>
            <follow_track>2</follow_track>
            <invert_mute>2</invert_mute>
            <mute_mode>1.0</mute_mode>
          </options>
        </Mixer>
      </applications>
    </touchosc_mixer_recorder_matrix>
    <microkontrol_mixer>
      <autostart>false</autostart>
      <device_port_in/>
      <device_port_out/>
      <applications>
        <Mixer>
          <options>
            <track_offset>1.0</track_offset>
            <page_size>1.0</page_size>
            <sync_pre_post>1.0</sync_pre_post>
            <pre_post>2</pre_post>
            <follow_track>2</follow_track>
            <invert_mute>2</invert_mute>
            <mute_mode>1.0</mute_mode>
          </options>
        </Mixer>
      </applications>
    </microkontrol_mixer>
    <microkontrol_effect>
      <autostart>false</autostart>
      <device_port_in/>
      <device_port_out/>
      <applications>
        <Effect>
          <options>
            <include_parameters>1.0</include_parameters>
          </options>
        </Effect>
      </applications>
    </microkontrol_effect>
    <nanokontrol_mixer_transport>
      <autostart>false</autostart>
      <device_port_in/>
      <device_port_out/>
      <applications>
        <Transport>
          <options>
            <pattern_play>1.0</pattern_play>
            <pattern_stop>1.0</pattern_stop>
            <pattern_switch>1.0</pattern_switch>
            <jump_mode>1.0</jump_mode>
          </options>
        </Transport>
        <Mixer>
          <options>
            <track_offset>1.0</track_offset>
            <page_size>1.0</page_size>
            <sync_pre_post>1.0</sync_pre_post>
            <pre_post>1.0</pre_post>
            <follow_track>2</follow_track>
            <invert_mute>2</invert_mute>
            <mute_mode>1.0</mute_mode>
          </options>
        </Mixer>
      </applications>
    </nanokontrol_mixer_transport>
    <uc33e_mixer_effects>
      <autostart>true</autostart>
      <device_port_in>UC-33 USB MIDI Controller (Port 1)</device_port_in>
      <device_port_out/>
      <applications>
        <Effect>
          <options>
            <include_parameters>1.0</include_parameters>
          </options>
        </Effect>
        <TrackSelector>
          <options>
            <page_size>1.0</page_size>
          </options>
        </TrackSelector>
        <Mixer>
          <options>
            <track_offset>1.0</track_offset>
            <page_size>1.0</page_size>
            <sync_pre_post>1.0</sync_pre_post>
            <pre_post>2</pre_post>
            <follow_track>2</follow_track>
            <invert_mute>2</invert_mute>
            <mute_mode>1.0</mute_mode>
          </options>
        </Mixer>
      </applications>
    </uc33e_mixer_effects>
  </configurations>
</ScriptingToolPreferences>
